pkrdatamapper/__init__.py
pkrdatamapper/manage.py
pkrdatamapper/PokerDataMapper/__init__.py
pkrdatamapper/PokerDataMapper/asgi.py
pkrdatamapper/PokerDataMapper/db_config.py
pkrdatamapper/PokerDataMapper/env_settings.py
pkrdatamapper/PokerDataMapper/settings.py
pkrdatamapper/PokerDataMapper/urls.py
pkrdatamapper/PokerDataMapper/wsgi.py
pkrdatamapper/actions/__init__.py
pkrdatamapper/actions/admin.py
pkrdatamapper/actions/apps.py
pkrdatamapper/actions/models.py
pkrdatamapper/actions/populate_db.py
pkrdatamapper/actions/tests.py
pkrdatamapper/actions/views.py
pkrdatamapper/actions/action_move/__init__.py
pkrdatamapper/actions/action_move/models.py
pkrdatamapper/actions/actions_sequence/__init__.py
pkrdatamapper/actions/actions_sequence/models.py
pkrdatamapper/actions/blind_type/__init__.py
pkrdatamapper/actions/blind_type/models.py
pkrdatamapper/actions/migrations/0001_initial.py
pkrdatamapper/actions/migrations/__init__.py
pkrdatamapper/actions/street/__init__.py
pkrdatamapper/actions/street/models.py
pkrdatamapper/cards/__init__.py
pkrdatamapper/cards/admin.py
pkrdatamapper/cards/apps.py
pkrdatamapper/cards/models.py
pkrdatamapper/cards/populate_db.py
pkrdatamapper/cards/signals.py
pkrdatamapper/cards/tests.py
pkrdatamapper/cards/views.py
pkrdatamapper/cards/card/__init__.py
pkrdatamapper/cards/card/models.py
pkrdatamapper/cards/combo/__init__.py
pkrdatamapper/cards/combo/models.py
pkrdatamapper/cards/flop/__init__.py
pkrdatamapper/cards/flop/models.py
pkrdatamapper/cards/hand/__init__.py
pkrdatamapper/cards/hand/models.py
pkrdatamapper/cards/migrations/0001_initial.py
pkrdatamapper/cards/migrations/__init__.py
pkrdatamapper/cards/rank/__init__.py
pkrdatamapper/cards/rank/models.py
pkrdatamapper/cards/shape/__init__.py
pkrdatamapper/cards/shape/models.py
pkrdatamapper/cards/suit/__init__.py
pkrdatamapper/cards/suit/models.py
pkrdatamapper/cards/suit/tests.py
pkrdatamapper/common/__init__.py
pkrdatamapper/common/fields.py
pkrdatamapper/common/mixins.py
pkrdatamapper-0.0.1.dist-info/LICENSE.txt
pkrdatamapper-0.0.1.dist-info/METADATA
pkrdatamapper-0.0.1.dist-info/WHEEL
pkrdatamapper-0.0.1.dist-info/top_level.txt
pkrdatamapper-0.0.1.dist-info/RECORD
