Metadata-Version: 2.1
Name: pkrdatamapper
Version: 0.0.1
Summary: A package to transform pkrcomponents objects into Database info
Home-page: https://github.com/manggy94/
Author: Alexandre MANGWA
Author-email: alex.mangwa@gmail.com
Project-URL: Bug Tracker, https://github.com/manggy94//issues
Classifier: Development Status :: 4 - Beta
Classifier: Intended Audience :: Developers
Classifier: License :: OSI Approved :: MIT License
Classifier: Natural Language :: English
Classifier: Programming Language :: Python
Classifier: Programming Language :: Python :: 3
Requires-Python: >=3.10
License-File: LICENSE.txt
